.gitignore
LICENSE.md
README.md
__init__.py
setup.py
utils.py
xmltojson.py
scripts/xmltojson
xmltojson.egg-info/PKG-INFO
xmltojson.egg-info/SOURCES.txt
xmltojson.egg-info/dependency_links.txt
xmltojson.egg-info/requires.txt
xmltojson.egg-info/top_level.txt