Metadata-Version: 1.1
Name: xmltojson
Version: 0.2.0
Summary: A Python module and cli tool to quickly convert xml text or files into json.
Home-page: https://github.com/shanahanjrs/xmltojson
Author: John Shanahan
Author-email: shanahan.jrs@gmail.com
License: Apache
Keywords: xml to json converter
Platform: UNKNOWN
Classifier: Development Status :: 4 - Beta
Classifier: Intended Audience :: Developers
Classifier: License :: OSI Approved :: Apache Software License
Classifier: Operating System :: MacOS :: MacOS X
Classifier: Operating System :: POSIX :: Linux
